acmc/__init__.py
acmc/__main__.py
acmc/logging_config.py
acmc/main.py
acmc/omop.py
acmc/parse.py
acmc/phen.py
acmc/trud.py
acmc/util.py
acmc-1.0.0.dist-info/METADATA
acmc-1.0.0.dist-info/WHEEL
acmc-1.0.0.dist-info/entry_points.txt
acmc-1.0.0.dist-info/licenses/LICENSE
acmc-1.0.0.dist-info/RECORD
