Metadata-Version: 2.4
Name: acmc
Version: 1.0.0
Summary: A Tool for Automating the Curation of Medical Concepts derived from Coding Lists
Project-URL: Repository, https://git.soton.ac.uk/meldb/concepts-processing
Project-URL: Documentation, https://acmc.readthedocs.io/en/latest/
Project-URL: Issues, https://git.soton.ac.uk/meldb/concepts-processing/-/issues
Author-email: Jakub Dylag <j.j.dylag@soton.ac.uk>, Michael Boniface <m.j.boniface@soton.ac.uk>
License:                                  Apache License
License-File: LICENSE
Requires-Python: >=3.9
Requires-Dist: aiosqlite
Requires-Dist: cerberus
Requires-Dist: click
Requires-Dist: cramjam
Requires-Dist: deepdiff
Requires-Dist: et-xmlfile
Requires-Dist: fastparquet
Requires-Dist: fsspec
Requires-Dist: gitdb
Requires-Dist: gitpython
Requires-Dist: greenlet
Requires-Dist: iniconfig
Requires-Dist: lxml
Requires-Dist: numpy
Requires-Dist: openpyxl
Requires-Dist: pandas-stubs
Requires-Dist: pluggy
Requires-Dist: pyarrow
Requires-Dist: pyomop
Requires-Dist: pytest
Requires-Dist: pyyaml
Requires-Dist: requests
Requires-Dist: semver
Requires-Dist: simpledbf
Requires-Dist: smmap
Requires-Dist: sqlalchemy
Requires-Dist: tables
Requires-Dist: types-pyyaml
Requires-Dist: types-requests
